salmiak/__init__.py
salmiak-0.3.dist-info/DESCRIPTION.rst
salmiak-0.3.dist-info/METADATA
salmiak-0.3.dist-info/RECORD
salmiak-0.3.dist-info/WHEEL
salmiak-0.3.dist-info/entry_points.txt
salmiak-0.3.dist-info/metadata.json
salmiak-0.3.dist-info/top_level.txt
